spectralpy/__init__.py
spectralpy/conftest.py
spectralpy/examples/examples.py
spectralpy/source/spectral_processing.py
spectralpy/test/shorthand.py
spectralpy/test/test_power_extraction.py
spectralpy/test/test_power_spectrum.py
spectralpy/test/data/NL1~modulation_amplitude=10.0V.csv
spectralpy/test/data/NL_test_data_10k.csv
spectralpy-0.1.14.dist-info/LICENSE.txt
spectralpy-0.1.14.dist-info/METADATA
spectralpy-0.1.14.dist-info/WHEEL
spectralpy-0.1.14.dist-info/top_level.txt
spectralpy-0.1.14.dist-info/RECORD
